nestees/__init__.py
nestees/fieldpath.py
nestees/nestees.py
nestees-1.0.1.dist-info/LICENSE
nestees-1.0.1.dist-info/METADATA
nestees-1.0.1.dist-info/WHEEL
nestees-1.0.1.dist-info/top_level.txt
nestees-1.0.1.dist-info/RECORD
