Metadata-Version: 2.1
Name: nestees
Version: 1.0.1
Summary: Utility functions for nested dictionaries (dict of dicts)
Home-page: https://github.com/maranite/nestees
Author: Mark White
Author-email: maranite@gmail.com
License: UNKNOWN
Project-URL: Bug Tracker, https://github.com/maranite/nestees/issues
Project-URL: About Mark, https://www.linkedin.com/in/maranite/
Platform: UNKNOWN
Classifier: Programming Language :: Python :: 3
Classifier: License :: OSI Approved :: MIT License
Classifier: Operating System :: OS Independent
Requires-Python: >=3.7
License-File: LICENSE
